{"0JL9TZip7mL7iwC5EOkALS": "Lady Brown (feat. Cise Starr from CYNE)", "5InOp6q2vvx0fShv3bzFLZ": "Know Yourself", "26xgfuQnTaa5UQJhdQACz6": "Forget", "5kVZxyMY1gfdCLiChsfjn1": "Yo No Soy Celoso", "5mCPDVBb16L4XQwDdbRUpz": "Passionfruit", "19vV1i1AluuK7mQcJmM5GZ": "Hermosura de Mujer", "7ovUcF5uHTBRzUpB6ZOmvt": "\u30a2\u30a4\u30c9\u30eb", "2ewjMyCbNv2X1dB2qIDCwD": "\u0398. Macarena", "3d3vEGKliS3341qCoNmkMC": "A Volta pra Casa", "6vnfObZ4Ys70SBAtti1xZ9": "COFFEE BEAN", "4x3205ovCyXtswRzLqEw0V": "Pegue Pra Ela", "0mb3xznNuQeYN2O3hxDZG5": "Plano de Voo", "6wsqVwoiVH2kde4k4KKAFU": "I KNOW ?", "5Tbpp3OLLClPJF8t1DmrFD": "Nuthin' But A \"G\" Thang", "3fX6IqwpcIYjyJwQFdJF8c": "Focused (feat. Young Thug)", "6sWBpYkVd1e8waQ8fNQ55p": "Kay Kay", "0CVt9RVUmKVEtYZTWH6mL1": "Humains - Bonus Track", "4voEoczU7Ijborps9XF1n3": "I Get Around"}